divewidgets/__init__.py
divewidgets/_frontend.py
divewidgets/_version.py
divewidgets/magic.py
divewidgets/widget.py
divewidgets/labextension/build_log.json
divewidgets/labextension/package.json
divewidgets/labextension/static/104.82af3596f7911dd7662d.js
divewidgets/labextension/static/282.d676d27d72b666c60ac1.js
divewidgets/labextension/static/365.14a518c310ad1aa47551.js
divewidgets/labextension/static/367.58ecdb72fd0974e0bee3.js
divewidgets/labextension/static/367.6682b4d6a2fc52425730.js
divewidgets/labextension/static/405.3cb69df6c0162b55c41e.js
divewidgets/labextension/static/480.ec977c2cd50a7e4ce523.js
divewidgets/labextension/static/480.f8baea077ec71f2e3df7.js
divewidgets/labextension/static/506.26626fb7dc8b1b4fe693.js
divewidgets/labextension/static/547.d46db7965b6a952582f2.js
divewidgets/labextension/static/568.69fe8895607d333de6bb.js
divewidgets/labextension/static/568.a0439c10bd6d0b61f72f.js
divewidgets/labextension/static/62.76968e599a008c83ae53.js
divewidgets/labextension/static/65.38af2dce42ddc9d22aff.js
divewidgets/labextension/static/653.df218904d2140e713fc3.js
divewidgets/labextension/static/705.9d259ab31e60fc2fda91.js
divewidgets/labextension/static/888.020adfd79659979c497d.js
divewidgets/labextension/static/91.73345f1c5294ba5134eb.js
divewidgets/labextension/static/986.aaddcfae0af8fa22dde4.js
divewidgets/labextension/static/lib_index_js.3b04ad1ccad8611db786.js
divewidgets/labextension/static/lib_index_js.3b04ad1ccad8611db786.js.map
divewidgets/labextension/static/lib_index_js.f61415d03112167cd5c6.js
divewidgets/labextension/static/lib_index_js.f61415d03112167cd5c6.js.map
divewidgets/labextension/static/lib_plugin_js.0144cf5c50ea30ef71cd.js
divewidgets/labextension/static/lib_plugin_js.0144cf5c50ea30ef71cd.js.map
divewidgets/labextension/static/lib_plugin_js.29a6db4c8b7260c2c649.js
divewidgets/labextension/static/lib_plugin_js.29a6db4c8b7260c2c649.js.map
divewidgets/labextension/static/lib_widget_js.30a74f90db455fc25d35.js
divewidgets-0.1.5.dist-info/LICENSE.txt
divewidgets-0.1.5.dist-info/METADATA
divewidgets-0.1.5.dist-info/WHEEL
divewidgets-0.1.5.dist-info/top_level.txt
divewidgets-0.1.5.dist-info/RECORD
